AstrixLibrary/__init__.py
AstrixLibrary/bot.py
astrixlibrary-1.0.3.1.dist-info/METADATA
astrixlibrary-1.0.3.1.dist-info/WHEEL
astrixlibrary-1.0.3.1.dist-info/top_level.txt
astrixlibrary-1.0.3.1.dist-info/RECORD
