Metadata-Version: 2.4
Name: astrixlibrary
Version: 1.0.3.1
Summary: A python library for creating bots in AstrixRU.
Home-page: https://astrixru.online
Author: Raphael Custos
Author-email: raphaelcustos@gmail.com
Classifier: Programming Language :: Python :: 3
Classifier: License :: OSI Approved :: MIT License
Classifier: Operating System :: OS Independent
Requires-Python: >=3.8
Requires-Dist: requests
Requires-Dist: python-socketio
Requires-Dist: websocket-client
Dynamic: author
Dynamic: author-email
Dynamic: classifier
Dynamic: description
Dynamic: description-content-type
Dynamic: home-page
Dynamic: requires-dist
Dynamic: requires-python
Dynamic: summary
